[{"orgname":"¹ãÖİ","data":[{"gust":"17","windforce":"6","windspeed":"12","time":"2015-08-10 14:00:00","rr07":"","pressure":"","passthrough":"0","name":"ËÕµÏÂŞ","longitude":"116.4","latitude":"30.8","distances":990},{"gust":"15","windforce":"5","windspeed":"10","time":"2015-08-11 02:00:00","rr07":"","pressure":"","passthrough":"1","name":"ËÕµÏÂŞ","longitude":"117.4","latitude":"31.6","LEADTIME":"12","distances":1110},{"gust":"15","windforce":"5","windspeed":"10","time":"2015-08-11 14:00:00","rr07":"","pressure":"","passthrough":"1","name":"ËÕµÏÂŞ","longitude":"120.9","latitude":"33.2","LEADTIME":"24","distances":1410}]}]